footballmodels/__init__.py
footballmodels/clustering/__init__.py
footballmodels/clustering/features.py
footballmodels/definitions/__init__.py
footballmodels/definitions/templates.py
footballmodels/model_files/__init__.py
footballmodels/model_files/pass_kmeans_model.model
footballmodels/model_files/pass_scaler.model
footballmodels/model_files/xpass_gb_v2.model
footballmodels/model_files/xpass_gb_v2_w_positions.model
footballmodels/model_files/xpass_v1.model
footballmodels/model_files/xpass_xgb_v2.model
footballmodels/model_files/xpass_xgb_v2_w_positions.model
footballmodels/opta/__init__.py
footballmodels/opta/actions.py
footballmodels/opta/dimensions.py
footballmodels/opta/distance.py
footballmodels/opta/event_type.py
footballmodels/opta/functions.py
footballmodels/opta/passes.py
footballmodels/opta/xpts.py
footballmodels/opta/aggregation/__init__.py
footballmodels/opta/aggregation/team_aggregation.py
footballmodels/player_similarity/__init__.py
footballmodels/player_similarity/column_defs.py
footballmodels/player_similarity/models.py
footballmodels/utils/__init__.py
footballmodels/utils/distance.py
footballmodels/utils/possession_adjustment.py
footballmodels/xpass/__init__.py
footballmodels/xpass/features.py
footballmodels/xpass/models.py
footballmodels/xt/__init__.py
footballmodels/xt/calcs.py
footballmodels-1.3.3.dist-info/licenses/LICENSE
footballmodels-1.3.3.dist-info/METADATA
footballmodels-1.3.3.dist-info/WHEEL
footballmodels-1.3.3.dist-info/top_level.txt
footballmodels-1.3.3.dist-info/RECORD
