Metadata-Version: 2.4
Name: footballmodels
Version: 1.3.3
Summary: Football Models library
Home-page: https://github.com/dmoggles/footballmodels
Author: Dmitry Mogilevsky
Author-email: dmitry.mogilevsky@gmail.com
License: MIT
Classifier: Development Status :: 3 - Alpha
Classifier: License :: OSI Approved :: MIT License
Classifier: Programming Language :: Python :: 3
Classifier: Programming Language :: Python :: 3.6
Classifier: Programming Language :: Python :: 3.7
Classifier: Programming Language :: Python :: 3.8
Classifier: Programming Language :: Python :: 3.9
Requires-Python: >=3.6
License-File: LICENSE
Requires-Dist: scikit-learn==1.5.2
Requires-Dist: pandas
Requires-Dist: joblib
Requires-Dist: xgboost==2.0.2
Provides-Extra: dev
Requires-Dist: pytest; extra == "dev"
Requires-Dist: black; extra == "dev"
Requires-Dist: pre-commit; extra == "dev"
Requires-Dist: pylint; extra == "dev"
Requires-Dist: pandas; extra == "dev"
Requires-Dist: joblib; extra == "dev"
Requires-Dist: xgboost==2.0.2; extra == "dev"
Dynamic: author
Dynamic: author-email
Dynamic: classifier
Dynamic: description
Dynamic: description-content-type
Dynamic: home-page
Dynamic: license
Dynamic: license-file
Dynamic: provides-extra
Dynamic: requires-dist
Dynamic: requires-python
Dynamic: summary
